{"Kukotsira": 6560, "Banda": 5635, "Nhova": 4944, "Misodzi": 4806, "Mucheche": 4732, "Mhanda (Kurwa)": 4745, "Sangano reHutano Pasirose": 6711, "Tsanga (ziso)": 4602, "Chirwere cheEbola": 7993, "Sura": 5200, "Kufuta": 5458, "Chidenhi": 4136, "Chipatara": 4951, "Mhopo": 5719, "Hunzwi": 4768, "Dzingiswa": 4062, "Hutano": 4860, "Kurutsa": 5448, "Nyamukuta": 4821, "Moyo": 4061, "Nhumbu": 4450, "Huropi": 4131, "Chapfunga": 4068, "Munyu": 4241, "Kufema": 5446, "Chimiro chemuviri": 4998, "Ronzaukadzi": 9829, "Chitunha": 4816, "Kurwadziwa": 5220, "Mutundo": 5319, "Chiremba": 4818, "Vanga": 4512, "Muzongoza": 4647, "Kukumbana": 8903, "Husimbe": 5965}