{"Datura": 2263459, "Cryptococcus_gattii": 1761810, "Heterophyidae": 365498, "Saposhnikovia_divaricata": 2300920, "Siberkondriya": 56969, "Pthirus_gorillae": 937917, "Tetraphyllidea": 370875, "Oestridae": 1390132, "Avicena": 55559, "Vitellaria_paradoxa": 2220741, "Onchocercidae": 200300, "Repluhong_laringgoparingheo": 59507, "Anopheles_dirus": 1313769, "Cryptococcus_neoformans": 1761755, "Catha_edulis": 2333110, "Heteracanthocephalidae": 114374, "Polymorphida": 113522, "Arsenico": 62552, "Agaricus_subrufescens": 1777205, "Tawo": 330652, "Microsporum_gypseum": 1861573, "2009_pandemya_sa_trangkaso_sa_Pilipinas": 50247, "Monhysterida": 198504, "Ospital": 36924, "Kabungol": 37486, "Biomphalaria": 79957, "Clonorchis_sinensis": 365646, "Agaricus_xanthodermus": 1777128, "Garapata": 242092, "Haycocknema_perplexum": 199233, "Diabetes_mellitus": 2800039, "Pm": 62889, "Echinorhynchida": 114052, "Geel_(lungsod)": 2996081, "Palaeacanthocephala": 113520, "Candida_dubliniensis": 1868530, "Kalsiyum": 62608, "Alpinia_nigra": 2291931, "Cheyletiella": 497687, "Echinostoma_revolutum": 364641, "Macracanthorhynchus_hirudinaceus": 115246, "Acanthocephalus": 114404, "Ancylostomatidae": 200343, "Mitragyna_speciosa": 2744825, "Pakighilawas": 37132, "Neprolohiya": 38158, "Wuchereria_bancrofti": 200308, "Rugogaster": 364028, "Medisina": 990, "Sip-on": 45228, "Utot": 44281, "Eoacanthocephala": 114746, "Alasinon": 59429, "Toxocara_canis": 199544, "Etanol": 54362, "Opisthorchis_viverrini": 365634, "Candida_tropicalis": 1868846, "Trichostrongylus": 200615, "Neoechinorhynchida": 114748, "Blaste": 881207, "Taeniidae": 372242, "Boswellia": 2675682, "Jasminum_officinale": 2584299, "Tenuisentidae": 114750, "Kasingkasing": 2327787, "Kasaysayan_sa_pagsukod_sa_presyon_sa_dugo": 34932, "Euphorbiaceae": 2414734, "Estrok": 38174, "Trichuridae": 199214, "Panglawas": 41469, "Toxicodendron": 2675082, "Toxocaridae": 199502, "Depresyon": 1883378, "Ginkgo_biloba": 2541295, "Magnesyo": 2379, "Haploporidae": 364670, "Hirudo_medicinalis": 146629, "Ancylostoma": 200345, "Diphyllobothrium": 370865, "Kamatayon": 38156, "Uhong": 1761507, "Ancylostoma_tubaeforme": 200351, "Archiacanthocephala": 115044, "Apodemus_agrarius": 329080, "Leonardo_da_Vinci": 3591857, "Alta_presyon": 34931, "Cimex_lectularius": 797282, "Sarcoptes_scabiei": 297358, "Atake_sa_kasingkasing": 38242, "Dipylidium_caninum": 372178, "Bacteria": 551285}